AUTHORS.rst
CONTRIBUTING.rst
HISTORY.rst
LICENSE
MANIFEST.in
README.rst
setup.py
lazyconn/__init__.py
lazyconn/globals.py
lazyconn/lazyconn.py
lazyconn/local.py
lazyconn.egg-info/PKG-INFO
lazyconn.egg-info/SOURCES.txt
lazyconn.egg-info/dependency_links.txt
lazyconn.egg-info/not-zip-safe
lazyconn.egg-info/top_level.txt