Metadata-Version: 1.1
Name: lazyconn
Version: 0.1.0
Summary: A lazy connection context manager
Home-page: https://github.com/youngking/lazyconn
Author: Young King
Author-email: y@zhihu.com
License: BSD
Keywords: lazyconn
Platform: UNKNOWN
Classifier: Development Status :: 2 - Pre-Alpha
Classifier: Intended Audience :: Developers
Classifier: License :: OSI Approved :: BSD License
Classifier: Natural Language :: English
Classifier: Programming Language :: Python :: 2
Classifier: Programming Language :: Python :: 2.7
Classifier: Programming Language :: Python :: 3
Classifier: Programming Language :: Python :: 3.3
